reqMock/__init__.py
reqMock/reqMock.py
reqMock-0.0.0.4.dist-info/METADATA
reqMock-0.0.0.4.dist-info/WHEEL
reqMock-0.0.0.4.dist-info/top_level.txt
reqMock-0.0.0.4.dist-info/RECORD
